{
    "columns": [
        {
            "prop": "id",
            "label": "会员id",
            "disabled": false
        },
        {
            "prop": "name",
            "label": "会员账号",
            "width": "100",
            "disabled": true
        },
        {
            "prop": "level",
            "label": "会员层级",
            "width": "100",
            "disabled": true,
            "filters": [
                {
                    "value": "1",
                    "text": "VIP 1"
                },
                {
                    "value": "2",
                    "text": "VIP 2"
                },
                {
                    "value": "3",
                    "text": "VIP 3"
                },
                {
                    "value": "4",
                    "text": "VIP 4"
                },
                {
                    "value": "5",
                    "text": "VIP 5"
                },
                {
                    "value": "6",
                    "text": "VIP 6"
                },
                {
                    "value": "7",
                    "text": "VIP 7"
                },
                {
                    "value": "8",
                    "text": "VIP 8"
                },
                {
                    "value": "9",
                    "text": "VIP 9"
                },
                {
                    "value": "10",
                    "text": "VIP 10"
                }
            ]
        },

        {
            "prop": "agent",
            "label": "所属代理",
            "width": "100",
            "disabled": true
        },
        {
            "prop": "created",
            "label": "会员加入时间",
            "width": "170",
            "disabled": true
        },
        {
            "prop": "last_login",
            "label": "最后登录时间",
            "width": "170",
            "disabled": true
        },
        {
            "prop": "deposit_total",
            "label": "存款次数",
            "sort": true,
            "width": "100",
            "disabled": true
        },
        {
            "prop": "deposit_money",
            "label": "存款总额",
            "sort": true,
            "width": "100",
            "type": "divisionMoney",
            "disabled": true
        },
        {
            "prop": "deposit_max",
            "label": "最大存款总额",
            "type": "divisionMoney",
            "sort": true,
            "width": "130",
            "disabled": true
        },
        {
            "prop": "withdraw_total",
            "label": "提现次数",
            "sort": true,
            "width": "100",
            "disabled": true
        },
        {
            "prop": "withdraw_money",
            "label": "提现总额",
            "type": "divisionMoney",
            "width": "120",
            "disabled": true
        },
        {
            "prop": "lid",
            "label": "分层",
            "width": "150",
            "type": "list",
            "disabled": true
        },
        {
            "prop": "lock",
            "label": "锁定",
            "width": "80",
            "checkbox": true,
            "disabled": true,
            "type": "switch"
        }
    ]
}
